sdk/__init__.py
sdk/main.py
sdk/adapters/__init__.py
sdk/adapters/h2h_payment_adapter.py
sdk/adapters/hosted_payment_adapter.py
sdk/adapters/hosted_quix_payment_adapter.py
sdk/adapters/js_payment_adapter.py
sdk/adapters/js_quix_payment_adapter.py
sdk/adapters/network_adapter.py
sdk/adapters/notification_adapter.py
sdk/enums/__init__.py
sdk/enums/category.py
sdk/enums/challenge_ind.py
sdk/enums/country_code.py
sdk/enums/currency.py
sdk/enums/endpoints.py
sdk/enums/environment.py
sdk/enums/error.py
sdk/enums/h2h_operation_type.py
sdk/enums/language.py
sdk/enums/merchant_exemptions_sca.py
sdk/enums/method.py
sdk/enums/operation_types.py
sdk/enums/payment_recurring_type.py
sdk/enums/payment_solutions.py
sdk/enums/response_codes.py
sdk/enums/transaction.py
sdk/exceptions/__init__.py
sdk/exceptions/field_exception.py
sdk/models/__init__.py
sdk/models/credentials.py
sdk/models/quix_models/__init__.py
sdk/models/quix_models/confirmation_cart_data.py
sdk/models/quix_models/customer.py
sdk/models/quix_models/quix_address.py
sdk/models/quix_models/quix_billing.py
sdk/models/quix_models/quix_hosted_request.py
sdk/models/quix_models/quix_js_request.py
sdk/models/quix_models/quix_shipping.py
sdk/models/quix_models/quix_accommodation/__init__.py
sdk/models/quix_models/quix_accommodation/auix_accommodation_cart_item.py
sdk/models/quix_models/quix_accommodation/auix_article_accommodation.py
sdk/models/quix_models/quix_accommodation/quix_accommodation_pay_sol_extended_data.py
sdk/models/quix_models/quix_accommodation/quix_cart_accommodation.py
sdk/models/quix_models/quix_flight/__init__.py
sdk/models/quix_models/quix_flight/quix_article_flight.py
sdk/models/quix_models/quix_flight/quix_cart_flight.py
sdk/models/quix_models/quix_flight/quix_flight_cart_item.py
sdk/models/quix_models/quix_flight/quix_flight_pay_sol_extended_data.py
sdk/models/quix_models/quix_flight/quix_passenger_flight.py
sdk/models/quix_models/quix_flight/quix_segment_flight.py
cgp_payment_sdk-1.0.4.dist-info/LICENSE
cgp_payment_sdk-1.0.4.dist-info/METADATA
cgp_payment_sdk-1.0.4.dist-info/WHEEL
cgp_payment_sdk-1.0.4.dist-info/top_level.txt
cgp_payment_sdk-1.0.4.dist-info/RECORD
