Metadata-Version: 2.1
Name: cgp-payment-sdk
Version: 1.0.4
Summary: Comercia Global Payments - Python SDK
Author: Comercia Global Payments
Classifier: Development Status :: 5 - Production/Stable
Classifier: Intended Audience :: Developers
Classifier: Intended Audience :: Financial and Insurance Industry
Classifier: Programming Language :: Python :: 3
Classifier: Operating System :: OS Independent
Classifier: License :: OSI Approved :: MIT License
License-File: LICENSE
Requires-Dist: dataclasses-json ==0.6.7
Requires-Dist: validators ==0.29.0
Requires-Dist: requests ==2.32.3
Requires-Dist: urllib3 ==2.2.2
Requires-Dist: certifi ==2024.6.2
Requires-Dist: charset-normalizer ==3.3.2
Requires-Dist: idna ==3.7
Requires-Dist: marshmallow ==3.21.3
Requires-Dist: mypy-extensions ==1.0.0
Requires-Dist: packaging ==24.1
Requires-Dist: pycryptodome ==3.20.0
Requires-Dist: typing-inspect ==0.9.0
Requires-Dist: typing-extensions ==4.12.2
